pillod/__init__.py
pillod/colortools.py
pillod/configtools.py
pillod/consoletools.py
pillod/datetools.py
pillod/dicttools.py
pillod/encryptiontools.py
pillod/filetools.py
pillod/hashtools.py
pillod/jsontools.py
pillod/listtools.py
pillod/mathtools.py
pillod/parsertools.py
pillod/pathtools.py
pillod/randomtools.py
pillod/regextools.py
pillod/sorttools.py
pillod/stringtools.py
pillod/validators.py
pillod-0.4.0.dist-info/LICENSE
pillod-0.4.0.dist-info/METADATA
pillod-0.4.0.dist-info/WHEEL
pillod-0.4.0.dist-info/top_level.txt
pillod-0.4.0.dist-info/RECORD
