Metadata-Version: 2.1
Name: pillod
Version: 0.4.0
Summary: A comprehensive Python utility library with 220+ functions across 18 modules
Home-page: https://github.com/DaRealTrueBlue/pillod
Author: DRTB
Author-email: darealtrueblue.contact@gmail.com
Project-URL: Bug Reports, https://github.com/DaRealTrueBlue/pillod/issues
Project-URL: Source, https://github.com/DaRealTrueBlue/pillod
Keywords: utilities tools parser string math list validators date random file config encryption console
Classifier: Programming Language :: Python :: 3
Classifier: Programming Language :: Python :: 3.7
Classifier: Programming Language :: Python :: 3.8
Classifier: Programming Language :: Python :: 3.9
Classifier: Programming Language :: Python :: 3.10
Classifier: Programming Language :: Python :: 3.11
Classifier: License :: OSI Approved :: MIT License
Classifier: Operating System :: OS Independent
Classifier: Development Status :: 4 - Beta
Classifier: Intended Audience :: Developers
Classifier: Topic :: Software Development :: Libraries :: Python Modules
Classifier: Topic :: Utilities
Requires-Python: >=3.7
License-File: LICENSE
